LICENCE
README.md
setup.cfg
setup.py
pyanxdns/__init__.py
pyanxdns/cli.py
pyanxdns/core.py
pyanxdns/helpers.py
pyanxdns/main.py
pyanxdns.egg-info/PKG-INFO
pyanxdns.egg-info/SOURCES.txt
pyanxdns.egg-info/dependency_links.txt
pyanxdns.egg-info/requires.txt
pyanxdns.egg-info/top_level.txt