Metadata-Version: 2.1
Name: pyanxdns
Version: 0.2.5
Summary: Python client to communicate with ANX DNS API
Home-page: https://github.com/egeback/pyanxdns
Author: Marky Egebäck
Author-email: marky@egeback.se
License: MIT
Platform: UNKNOWN
Classifier: Development Status :: 3 - Alpha
Classifier: Intended Audience :: Developers
Classifier: License :: OSI Approved :: MIT License
Classifier: Programming Language :: Python
Classifier: Programming Language :: Python :: 2
Classifier: Programming Language :: Python :: 3
Classifier: Topic :: Utilities
License-File: LICENCE
